<CodeEditorModel xmlns="http://schemas.datacontract.org/2004/07/Omron.Cxap.Modules.DeviceHmi.CodeEditor.Core" xmlns:i="http://www.w3.org/2001/XMLSchema-instance"><CodingLanguageName>VBNET</CodingLanguageName><HiddenFooter>&#xD;
End Class</HiddenFooter><HiddenHeader>Partial Public Class Main_Page&#xD;
</HiddenHeader><SerialData i:type="a:string" xmlns:a="http://www.w3.org/2001/XMLSchema">{"c":[]}</SerialData><SerialDeviceHmiId i:type="a:string" xmlns:a="http://www.w3.org/2001/XMLSchema">{"c":["{\"t\":\"System.String\",\"a\":\"mscorlib, Version=4.0.0.0, Culture=neutral, PublicKeyToken=b77a5c561934e089\",\"o\":\"025dd193-45aa-4b35-973d-b5810cd3ea85\"}","{\"t\":\"System.String\",\"a\":\"mscorlib, Version=4.0.0.0, Culture=neutral, PublicKeyToken=b77a5c561934e089\",\"o\":\"92f64893-47ad-497f-b015-d10894f70764\"}"]}</SerialDeviceHmiId><SerialScaleData i:type="a:string" xmlns:a="http://www.w3.org/2001/XMLSchema">{"c":[]}</SerialScaleData><Text>'Code derrière page - Ajouter des sous-programmes locaux pour la page.&#xD;
</Text></CodeEditorModel>